easylambda/__init__.py
easylambda/aws.py
easylambda/body.py
easylambda/dependency.py
easylambda/depends.py
easylambda/errors.py
easylambda/header.py
easylambda/main.py
easylambda/method_router.py
easylambda/path.py
easylambda/query.py
easylambda-0.2.4.dist-info/LICENSE
easylambda-0.2.4.dist-info/METADATA
easylambda-0.2.4.dist-info/WHEEL
easylambda-0.2.4.dist-info/RECORD
