Metadata-Version: 2.3
Name: easylambda
Version: 0.2.4
Summary: 
License: MIT
Author: Leandro Lima
Author-email: leandro@lls-software.com
Requires-Python: >=3.12,<4.0
Classifier: License :: OSI Approved :: MIT License
Classifier: Programming Language :: Python :: 3
Classifier: Programming Language :: Python :: 3.12
Classifier: Programming Language :: Python :: 3.13
Requires-Dist: pydantic (>=2.9.2,<3.0.0)
